{
    "route": "/compare-pdf",
    "title": "Free Online PDF Comparison - Compare PDF Files | Uvero",
    "description": "Compare two PDF files side by side online for free. Find differences between document versions. Works in your browser.",
    "keywords": [
        "compare pdf",
        "pdf comparison",
        "diff pdf",
        "pdf difference",
        "compare documents",
        "document comparison"
    ],
    "ogImage": "/og-compare-pdf.png",
    "canonical": "https://uvero.app/compare-pdf"
}
